fastrpa/__init__.py
fastrpa/app.py
fastrpa/core/console.py
fastrpa/core/cookies.py
fastrpa/core/elements.py
fastrpa/core/elements_factory.py
fastrpa/core/file.py
fastrpa/core/keyboard.py
fastrpa/core/screenshot.py
fastrpa/core/tabs.py
fastrpa/core/wait.py
fastrpa/exceptions.py
fastrpa/types.py
fastrpa/utils.py
fastrpa/xpath.py
fastrpa-1.0.1.dist-info/LICENSE
fastrpa-1.0.1.dist-info/METADATA
fastrpa-1.0.1.dist-info/WHEEL
fastrpa-1.0.1.dist-info/RECORD
