Metadata-Version: 2.1
Name: fastrpa
Version: 1.0.1
Summary: A simple to use abstraction over Selenium
Home-page: https://github.com/jjpaulo2/fastrpa
License: BSD-2-Clause
Keywords: selenium,rpa,fastapi,easy,fast,automation,robot,browser
Author: João Paulo Carvalho
Author-email: jjpaulo2@protonmail.com
Requires-Python: >=3.10,<4.0
Classifier: License :: OSI Approved :: BSD License
Classifier: Programming Language :: Python :: 3
Classifier: Programming Language :: Python :: 3.10
Classifier: Programming Language :: Python :: 3.11
Classifier: Programming Language :: Python :: 3.12
Classifier: Topic :: Software Development :: Libraries
Classifier: Topic :: Software Development :: Libraries :: Python Modules
Classifier: Typing :: Typed
Provides-Extra: debug
Requires-Dist: requests (>=2.32.3,<3.0.0)
Requires-Dist: rich (>=13.7.1,<14.0.0) ; extra == "debug"
Requires-Dist: selenium (>=4.22.0,<5.0.0)
Requires-Dist: types-requests (>=2.32.0.20240622,<3.0.0.0)
Project-URL: Bug Tracker, https://github.com/jjpaulo2/fastrpa/issues
Project-URL: Documentation, https://jjpaulo2.github.io/fastrpa
Project-URL: Repository, https://github.com/jjpaulo2/fastrpa
